.gitmodules
LICENSE
MANIFEST.in
README.md
setup.cfg
setup.py
versioneer.py
src/__init__.py
src/__metadata__.py
src/_build_utils.py
src/_builtin_utils.py
src/_constants.py
src/_name.py
src/_version.py
src/versioneer.py
src/galaxia_ananke/Input.py
src/galaxia_ananke/Output.py
src/galaxia_ananke/Survey.py
src/galaxia_ananke/__init__.py
src/galaxia_ananke/__metadata__.py
src/galaxia_ananke/_builtin_utils.py
src/galaxia_ananke/_constants.py
src/galaxia_ananke/_defaults.py
src/galaxia_ananke/_name.py
src/galaxia_ananke/_templates.py
src/galaxia_ananke/_version.py
src/galaxia_ananke/utils.py
src/galaxia_ananke.egg-info/PKG-INFO
src/galaxia_ananke.egg-info/SOURCES.txt
src/galaxia_ananke.egg-info/dependency_links.txt
src/galaxia_ananke.egg-info/requires.txt
src/galaxia_ananke.egg-info/top_level.txt
src/galaxia_ananke/__license__/LICENSE
src/galaxia_ananke/__license__/__init__.py
src/galaxia_ananke/photometry/Formatting.py
src/galaxia_ananke/photometry/InterfaceSvoFpsDriver.py
src/galaxia_ananke/photometry/Isochrone.py
src/galaxia_ananke/photometry/IsochroneFile.py
src/galaxia_ananke/photometry/PhotoSystem.py
src/galaxia_ananke/photometry/Photometry.py
src/galaxia_ananke/photometry/SvoFpsDriver.py
src/galaxia_ananke/photometry/__init__.py