Metadata-Version: 2.4
Name: galaxia_ananke
Version: 0.6.1
Summary: py-Galaxia-ananke: Python wrapper for a modified version of Galaxia (Sharma et al. 2011 <http://ascl.net/1101.007>) for py-ananke <https://github.com/athob/py-ananke>.
Home-page: https://github.com/athob/py-Galaxia-ananke
Author: Adrien Thob
Author-email: athob@sas.upenn.edu
Maintainer: Adrien Thob
Maintainer-email: athob@sas.upenn.edu
Classifier: Development Status :: 5 - Production/Stable
Classifier: Environment :: Console
Classifier: Intended Audience :: Science/Research
Classifier: License :: OSI Approved :: GNU General Public License v3 or later (GPLv3+)
Classifier: Natural Language :: English
Classifier: Operating System :: Unix
Classifier: Programming Language :: Python :: 3
Classifier: Topic :: Scientific/Engineering :: Astronomy
Requires-Python: >=3.8,<3.11
License-File: LICENSE
Requires-Dist: numpy<2,>=1.22
Requires-Dist: pandas<3,>=2
Requires-Dist: vaex<5,>=4.17
Requires-Dist: astropy<7,>=5
Requires-Dist: h5py<4,>=3.6
Requires-Dist: ebfpy<1,>=0.0.20
Requires-Dist: astroquery<1,>=0.4.2
Requires-Dist: pathos<1,>=0.3.3
Dynamic: author
Dynamic: author-email
Dynamic: classifier
Dynamic: description
Dynamic: description-content-type
Dynamic: home-page
Dynamic: license-file
Dynamic: maintainer
Dynamic: maintainer-email
Dynamic: requires-dist
Dynamic: requires-python
Dynamic: summary
